ArticleAnalyst/__init__.py
ArticleAnalyst/articleAnalyst.py
ArticleAnalyst/settings.py
ArticleAnalyst/function/__init__.py
ArticleAnalyst/function/annotation.py
ArticleAnalyst/function/article.py
ArticleAnalyst/function/document.py
ArticleAnalyst/function/downloader.py
ArticleAnalyst/function/meshAnalyst.py
articleanalyst-0.0.4.dist-info/METADATA
articleanalyst-0.0.4.dist-info/WHEEL
articleanalyst-0.0.4.dist-info/licenses/LICENSE
articleanalyst-0.0.4.dist-info/RECORD
